LICENSE
MANIFEST.in
README.rst
setup.py
examples/autoscroll/autoscroll.py
examples/autoscroll/client.py
examples/autoscroll/index.html
examples/autoscroll/styles.styl
examples/hello_world/client.py
examples/hello_world/hello.py
examples/hello_world/index.html
examples/progress_bar/client.py
examples/progress_bar/index.html
examples/progress_bar/progress.py
examples/progress_bar/styles.styl
examples/progress_bar_rapydscript/client.pyj
examples/progress_bar_rapydscript/index.html
examples/progress_bar_rapydscript/progress.py
examples/progress_bar_rapydscript/styles.styl
examples/read_news/client.pyj
examples/read_news/index.html
examples/read_news/read_news.py
examples/read_news/styles.styl
examples/stoppable/client.py
examples/stoppable/index.html
examples/stoppable/stoppable.py
quip/__init__.py
quip/compat.py
quip/runner.py
quip/server.py
quip.egg-info/PKG-INFO
quip.egg-info/SOURCES.txt
quip.egg-info/dependency_links.txt
quip.egg-info/not-zip-safe
quip.egg-info/requires.txt
quip.egg-info/top_level.txt
quip/resources/boilerplate.html
quip/resources/boilerplate_rapydscript.html
quip/resources/quipclient.py
quip/resources/quipclient.pyj